README.rst
setup.py
django_zesty_metrics.egg-info/PKG-INFO
django_zesty_metrics.egg-info/SOURCES.txt
django_zesty_metrics.egg-info/dependency_links.txt
django_zesty_metrics.egg-info/requires.txt
django_zesty_metrics.egg-info/top_level.txt
zesty_metrics/__init__.py
zesty_metrics/conf.py
zesty_metrics/defaults.py
zesty_metrics/forms.py
zesty_metrics/handlers.py
zesty_metrics/middleware.py
zesty_metrics/models.py
zesty_metrics/tests.py
zesty_metrics/tracking.py
zesty_metrics/urls.py
zesty_metrics/views.py
zesty_metrics/management/__init__.py
zesty_metrics/migrations/0001_initial.py
zesty_metrics/migrations/0002_auto__add_dailyactivityrecord__add_unique_dailyactivityrecord_user_wha.py
zesty_metrics/migrations/__init__.py