Metadata-Version: 1.1
Name: django-zesty-metrics
Version: 0.3.1
Summary: Zesty metrics collection and Statsd integration for Django.
Home-page: https://github.com/Crossway/django-zesty-metrics
Author: David Eyk
Author-email: deyk@crossway.org
License: BSD
Platform: UNKNOWN
Classifier: License :: OSI Approved :: BSD License
